chromadb_store/__init__.py
chromadb_store/engine.py
chromadb_store/py.typed
promptimus_chromadb_store-0.1.5.dist-info/METADATA
promptimus_chromadb_store-0.1.5.dist-info/WHEEL
promptimus_chromadb_store-0.1.5.dist-info/RECORD
